autosocks/__init__.py
autosocks/__main__.py
autosocks/storage.py
autosocks-0.1.0.dist-info/entry_points.txt
autosocks-0.1.0.dist-info/WHEEL
autosocks-0.1.0.dist-info/METADATA
autosocks-0.1.0.dist-info/RECORD
