Metadata-Version: 2.1
Name: autosocks
Version: 0.1.0
Summary: 
Author: Gerald
Author-email: gera2ld@live.com
Requires-Python: >=3.8,<4.0
Classifier: Programming Language :: Python :: 3
Classifier: Programming Language :: Python :: 3.8
Requires-Dist: gera2ld.socks (>=0.1.0,<0.2.0)
